{"Date": "20260625","KitchenNames": [
{"KitchenName":"金星餐盒食品有限公司","MemuList":{"StapleFood":"紫米飯",
"MainCourse":"美式雞腿排",
"SecondaryCourse1":"淋汁福州丸",
"SecondaryCourse2":"扁蒲燴炒",
"Vegetable":"鵝白菜",
"Soup":"冬瓜薑絲湯"
}}
,{"KitchenName":"昱品美食股份有限公司","MemuList":{"StapleFood":"糙米飯",
"MainCourse":"蠔菇燒豬柳",
"SecondaryCourse1":"糖醋腐丁",
"SecondaryCourse2":"法式焗白菜",
"Vegetable":"青江菜",
"Soup":"筍香魚丸湯"
}}
,{"KitchenName":"全富食品有限公司","MemuList":{"StapleFood":"客家粄條1",
"MainCourse":"香酥雞腿",
"SecondaryCourse1":"小瓜混炒1",
"SecondaryCourse2":"芝麻包",
"Vegetable":"炒高麗菜",
"Soup":"綜合豬血湯1"
}}
]}
